CherryTomato/__init__.py
CherryTomato/about_ui.py
CherryTomato/about_window.py
CherryTomato/main.py
CherryTomato/main_ui.py
CherryTomato/main_window.py
CherryTomato/settings.py
CherryTomato/settings_ui.py
CherryTomato/settings_window.py
CherryTomato/timer_proxy.py
CherryTomato/tomato_timer.py
CherryTomato/utils.py
CherryTomato/widget.py
CherryTomato/media/NotoSans-Regular.ttf
CherryTomato/media/icon.png
CherryTomato/media/play.png
CherryTomato/media/sound.wav
CherryTomato/media/stop.png
CherryTomato-1.1.0.dist-info/LICENSE
CherryTomato-1.1.0.dist-info/METADATA
CherryTomato-1.1.0.dist-info/WHEEL
CherryTomato-1.1.0.dist-info/entry_points.txt
CherryTomato-1.1.0.dist-info/top_level.txt
CherryTomato-1.1.0.dist-info/RECORD
