Metadata-Version: 2.1
Name: CherryTomato
Version: 1.1.0
Summary: Easy to use, flexible PyQt5 Pomodoro Technique timer.
Home-page: https://github.com/yakimka/CherryTomato
Author: yakimka
Author-email: ss.yakim@gmail.com
License: GPL-3.0
Platform: UNKNOWN
Classifier: Development Status :: 5 - Production/Stable
Classifier: Programming Language :: Python :: 3
Classifier: Intended Audience :: End Users/Desktop
Classifier: License :: OSI Approved :: GNU General Public License v3 (GPLv3)
Classifier: Topic :: Desktop Environment :: K Desktop Environment (KDE)
Classifier: Topic :: Utilities
Requires-Python: >=3.6
Requires-Dist: PyQt5 (~=5.15.1)
Requires-Dist: qroundprogressbar (~=1.0.0)
Provides-Extra: dev
Requires-Dist: flake8 ; extra == 'dev'
Requires-Dist: pytest ; extra == 'dev'
Requires-Dist: pytest-cov ; extra == 'dev'
Requires-Dist: pytest-mock ; extra == 'dev'
Requires-Dist: pytest-qt ; extra == 'dev'
